demoji/__init__.py
demoji_noprint-0.3.0.dist-info/LICENSE
demoji_noprint-0.3.0.dist-info/METADATA
demoji_noprint-0.3.0.dist-info/WHEEL
demoji_noprint-0.3.0.dist-info/top_level.txt
demoji_noprint-0.3.0.dist-info/RECORD
